PowerBI_Operator/__init__.py
PowerBI_Operator/hooks/__init__.py
PowerBI_Operator/hooks/powerbi_hook.py
PowerBI_Operator/models/__init__.py
PowerBI_Operator/models/powerbi_models.py
PowerBI_Operator/operators/__init__.py
PowerBI_Operator/operators/powerbi_refresh_dataset_operator.py
PowerBI_Operator/sensors/__init__.py
PowerBI_Operator/sensors/powerbi_refresh_dataset_sensor.py
airflow_powerbi_provider-1.1.2.dist-info/METADATA
airflow_powerbi_provider-1.1.2.dist-info/WHEEL
airflow_powerbi_provider-1.1.2.dist-info/licenses/LICENSE
airflow_powerbi_provider-1.1.2.dist-info/RECORD
