Metadata-Version: 2.4
Name: airflow-powerbi-provider
Version: 1.1.2
Summary: A provider package for Apache Airflow to refresh Powerbi Datasets
Project-URL: Homepage, https://github.com/gschuurman/airflow-powerbi-provider
Project-URL: Issues, https://github.com/gschuurman/airflow-powerbi-provider/issues
Author-email: Glenn Schuurman <info@schuurman-it.com>, Michael Schuurman <info@schuurman-it.com>
License-File: LICENSE
Classifier: License :: OSI Approved :: MIT License
Classifier: Programming Language :: Python :: 3
Requires-Python: >=3.10
Requires-Dist: apache-airflow>=2.10.0
Requires-Dist: azure-identity>=1.17.1
